salesanalyzer_mds/__init__.py
salesanalyzer_mds/predict_sales.py
salesanalyzer_mds/sales_summary_statistics.py
salesanalyzer_mds/segment_revenue_share.py
salesanalyzer_mds-2.1.2.dist-info/LICENSE
salesanalyzer_mds-2.1.2.dist-info/METADATA
salesanalyzer_mds-2.1.2.dist-info/WHEEL
salesanalyzer_mds-2.1.2.dist-info/RECORD
