Metadata-Version: 2.3
Name: salesanalyzer_mds
Version: 2.1.2
Summary: A Python package for sales forecasting, statistical analysis, and data-driven insights
License: MIT
Author: Daria Khon, Franklin Aryee, Yeji Sohn
Requires-Python: >=3.10
Classifier: License :: OSI Approved :: MIT License
Classifier: Programming Language :: Python :: 3
Classifier: Programming Language :: Python :: 3.10
Classifier: Programming Language :: Python :: 3.11
Classifier: Programming Language :: Python :: 3.12
Classifier: Programming Language :: Python :: 3.13
Requires-Dist: pandas (>=2.2.3)
Requires-Dist: scikit-learn (>=1.6.1)
